LICENSE
README.md
pyproject.toml
src/mmisp/worker/__init__.py
src/mmisp/worker/config.py
src/mmisp/worker/main.py
src/mmisp/worker/py.typed
src/mmisp/worker/redis_config.py
src/mmisp/worker/api/__init__.py
src/mmisp/worker/api/api_verification.py
src/mmisp/worker/api/job_router.py
src/mmisp/worker/api/requests_schemas.py
src/mmisp/worker/api/response_schemas.py
src/mmisp/worker/api/worker_router.py
src/mmisp/worker/controller/__init__.py
src/mmisp/worker/controller/connection_manager.py
src/mmisp/worker/controller/job_controller.py
src/mmisp/worker/controller/worker_controller.py
src/mmisp/worker/exceptions/__init__.py
src/mmisp/worker/exceptions/environment_exceptions.py
src/mmisp/worker/exceptions/job_exceptions.py
src/mmisp/worker/exceptions/misp_api_exceptions.py
src/mmisp/worker/exceptions/server_exceptions.py
src/mmisp/worker/jobs/__init__.py
src/mmisp/worker/jobs/all_jobs.py
src/mmisp/worker/jobs/all_queues.py
src/mmisp/worker/jobs/correlation/__init__.py
src/mmisp/worker/jobs/correlation/clean_excluded_correlations_job.py
src/mmisp/worker/jobs/correlation/correlation_config_data.py
src/mmisp/worker/jobs/correlation/correlation_job.py
src/mmisp/worker/jobs/correlation/fastapi_endpoints.py
src/mmisp/worker/jobs/correlation/job_data.py
src/mmisp/worker/jobs/correlation/queue.py
src/mmisp/worker/jobs/correlation/regenerate_occurrences_job.py
src/mmisp/worker/jobs/correlation/top_correlations_job.py
src/mmisp/worker/jobs/correlation/utility.py
src/mmisp/worker/jobs/correlation/worker.py
src/mmisp/worker/jobs/correlation/plugins/__init__.py
src/mmisp/worker/jobs/correlation/plugins/simple_value.py
src/mmisp/worker/jobs/debug/delayjob/__init__.py
src/mmisp/worker/jobs/debug/delayjob/delay_job.py
src/mmisp/worker/jobs/debug/delayjob/fastapi_endpoints.py
src/mmisp/worker/jobs/debug/delayjob/queue.py
src/mmisp/worker/jobs/email/__init__.py
src/mmisp/worker/jobs/email/alert_email_job.py
src/mmisp/worker/jobs/email/contact_email_job.py
src/mmisp_worker.egg-info/PKG-INFO
src/mmisp_worker.egg-info/SOURCES.txt
src/mmisp_worker.egg-info/dependency_links.txt
src/mmisp_worker.egg-info/entry_points.txt
src/mmisp_worker.egg-info/requires.txt
src/mmisp_worker.egg-info/top_level.txt